{
  "${ModID}:BlockOnPower": {
    "NAME": "Block-On",
    "DESCRIPTIONS": [
      "Whenever you are attacked this turn, apply #b%d #yLock-On back."
    ]
  },
  "${ModID}:LightningRodPower": {
    "NAME": "Lightning Rod",
    "DESCRIPTIONS": [
      "#yLightning targets this enemy this turn.",
      "#yLightning targets this enemy for #b%d turns."
    ]
  },
  "${ModID}:TunnelVisionPower": {
    "NAME": "Tunnel Vision",
    "DESCRIPTIONS": [
      "#yLock-On further increases #yOrb damage by #b25% per additional #yLock-On."
    ]
  },
  "${ModID}:GlockOnPower": {
    "NAME": "Glock-On",
    "DESCRIPTIONS": [
      "Attacks are affected by #yFocus and #yLock-On this turn.",
      "Attacks are affected by #yFocus and #yLock-On for the next #b",
      " turns."
    ]
  }
}
